NeuroInsight/__init__.py
NeuroInsight/activation_function.py
NeuroInsight/back_propagation.py
NeuroInsight/cost_function.py
NeuroInsight/evaluation.py
NeuroInsight/forward_propagation.py
NeuroInsight/one_hot_encoding.py
NeuroInsight/parameter_initialization.py
NeuroInsight/visualization.py
NeuroInsight-0.1.dist-info/LICENSE
NeuroInsight-0.1.dist-info/METADATA
NeuroInsight-0.1.dist-info/WHEEL
NeuroInsight-0.1.dist-info/top_level.txt
NeuroInsight-0.1.dist-info/RECORD
